[
    {
        "visible": false, 
        "name": "amateur", 
        "label": "amateur"
    }, 
    {
        "visible": false, 
        "name": "geostationary", 
        "label": "geostationary"
    }, 
    {
        "visible": false, 
        "name": "gps-ops", 
        "label": "gps-ops"
    }, 
    {
        "visible": false, 
        "name": "resource", 
        "label": "resource"
    }, 
    {
        "visible": false, 
        "name": "science", 
        "label": "science"
    }, 
    {
        "visible": false, 
        "name": "stations", 
        "label": "stations"
    }, 
    {
        "visible": true, 
        "name": "visible", 
        "label": "visible"
    }, 
    {
        "visible": false, 
        "name": "weather", 
        "label": "weather"
    }
]